fastapi_queryinspect.py
fastapi_queryinspect-0.1.4.dist-info/licenses/LICENSE
fastapi_queryinspect-0.1.4.dist-info/METADATA
fastapi_queryinspect-0.1.4.dist-info/WHEEL
fastapi_queryinspect-0.1.4.dist-info/top_level.txt
fastapi_queryinspect-0.1.4.dist-info/RECORD
